<DCRModel>
  <title>DCR from pm4py</title>
  <graphType>DCRModel</graphType>
  <roles>
    <title>User</title>
    <description>Dummy user</description>
  </roles>
  <events>
    <id>OCancelled</id>
    <label>OCancelled</label>
  </events>
  <rules>
    <type>exclude</type>
    <source>OCancelled</source>
    <target>OCancelled</target>
  </rules>
  <rules>
    <type>exclude</type>
    <source>OCancelled</source>
    <target>ORefused</target>
  </rules>
  <rules>
    <type>exclude</type>
    <source>OCancelled</source>
    <target>OAccepted</target>
  </rules>
  <rules>
    <type>condition</type>
    <source>OCreated</source>
    <target>OCancelled</target>
  </rules>
  <events>
    <id>OCreateOffer</id>
    <label>OCreateOffer</label>
  </events>
  <rules>
    <type>exclude</type>
    <source>OCreateOffer</source>
    <target>OCreateOffer</target>
  </rules>
  <rules>
    <type>response</type>
    <source>OCreateOffer</source>
    <target>OCreated</target>
  </rules>
  <events>
    <id>ORefused</id>
    <label>ORefused</label>
  </events>
  <rules>
    <type>exclude</type>
    <source>ORefused</source>
    <target>OCancelled</target>
  </rules>
  <rules>
    <type>exclude</type>
    <source>ORefused</source>
    <target>ORefused</target>
  </rules>
  <rules>
    <type>exclude</type>
    <source>ORefused</source>
    <target>OAccepted</target>
  </rules>
  <rules>
    <type>condition</type>
    <source>OCreated</source>
    <target>ORefused</target>
  </rules>
  <events>
    <id>OSentonlineonly</id>
    <label>OSentonlineonly</label>
  </events>
  <rules>
    <type>exclude</type>
    <source>OSentonlineonly</source>
    <target>OSentonlineonly</target>
  </rules>
  <rules>
    <type>condition</type>
    <source>OCreated</source>
    <target>OSentonlineonly</target>
  </rules>
  <rules>
    <type>exclude</type>
    <source>OSentonlineonly</source>
    <target>OSentmailandonline</target>
  </rules>
  <events>
    <id>OAccepted</id>
    <label>OAccepted</label>
  </events>
  <rules>
    <type>exclude</type>
    <source>OAccepted</source>
    <target>OCancelled</target>
  </rules>
  <rules>
    <type>exclude</type>
    <source>OAccepted</source>
    <target>ORefused</target>
  </rules>
  <rules>
    <type>exclude</type>
    <source>OAccepted</source>
    <target>OAccepted</target>
  </rules>
  <rules>
    <type>condition</type>
    <source>OReturned</source>
    <target>OAccepted</target>
  </rules>
  <events>
    <id>OCreated</id>
    <label>OCreated</label>
  </events>
  <rules>
    <type>condition</type>
    <source>OCreateOffer</source>
    <target>OCreated</target>
  </rules>
  <rules>
    <type>exclude</type>
    <source>OCreated</source>
    <target>OCreated</target>
  </rules>
  <events>
    <id>OReturned</id>
    <label>OReturned</label>
  </events>
  <rules>
    <type>condition</type>
    <source>OSentonlineonly</source>
    <target>OReturned</target>
  </rules>
  <rules>
    <type>exclude</type>
    <source>OReturned</source>
    <target>OReturned</target>
  </rules>
  <rules>
    <type>condition</type>
    <source>OSentmailandonline</source>
    <target>OReturned</target>
  </rules>
  <events>
    <id>OSentmailandonline</id>
    <label>OSentmailandonline</label>
  </events>
  <rules>
    <type>exclude</type>
    <source>OSentmailandonline</source>
    <target>OSentonlineonly</target>
  </rules>
  <rules>
    <type>condition</type>
    <source>OCreated</source>
    <target>OSentmailandonline</target>
  </rules>
  <rules>
    <type>exclude</type>
    <source>OSentmailandonline</source>
    <target>OSentmailandonline</target>
  </rules>
</DCRModel>
